Topsis/__init__.py
Topsis/topsis.py
topsis_102203210-1.1.0.dist-info/LICENSE
topsis_102203210-1.1.0.dist-info/METADATA
topsis_102203210-1.1.0.dist-info/WHEEL
topsis_102203210-1.1.0.dist-info/entry_points.txt
topsis_102203210-1.1.0.dist-info/top_level.txt
topsis_102203210-1.1.0.dist-info/RECORD
