Metadata-Version: 2.1
Name: topsis-102203210
Version: 1.1.0
Summary: A Python package for TOPSIS multi-criteria decision-making.
Home-page: https://github.com/reet1104/Topsis
Author: Anureet Kaur
Author-email: cheemaanureet2811@gmail.com
Classifier: Programming Language :: Python :: 3
Classifier: License :: OSI Approved :: MIT License
Classifier: Operating System :: OS Independent
Requires-Python: >=3.6
License-File: LICENSE
Requires-Dist: pandas
Requires-Dist: numpy
Requires-Dist: scipy
